crlint/__init__.py
crlint/__main__.py
crlint/exceptions.py
crlint/linting.py
crlint/utils.py
crlint-0.1.2.data/scripts/__main__.py
crlint-0.1.2.dist-info/LICENSE
crlint-0.1.2.dist-info/METADATA
crlint-0.1.2.dist-info/WHEEL
crlint-0.1.2.dist-info/entry_points.txt
crlint-0.1.2.dist-info/top_level.txt
crlint-0.1.2.dist-info/RECORD
